CHANGELOG.rst
LICENSE.txt
MANIFEST.in
README.rst
arte_plus7.py
setup.cfg
setup.py
tox.ini
arte_plus7.egg-info/PKG-INFO
arte_plus7.egg-info/SOURCES.txt
arte_plus7.egg-info/dependency_links.txt
arte_plus7.egg-info/entry_points.txt
arte_plus7.egg-info/requires.txt
arte_plus7.egg-info/top_level.txt