Metadata-Version: 1.1
Name: arte-plus7
Version: 2.2.4
Summary: CLI script to get videos from Arte plus 7 using their URL
Home-page: https://github.com/cladmi/arte_plus7
Author: cladmi
Author-email: hartergaetan@gmail.com
License: MIT
Download-URL: https://github.com/cladmi/arte_plus7
Platform: UNKNOWN
Classifier: Development Status :: 4 - Beta
Classifier: Programming Language :: Python
Classifier: Intended Audience :: End Users/Desktop
Classifier: Topic :: Utilities
